LICENSE
MANIFEST.in
README.rst
setup.cfg
setup.py
trio_websockets/__init__.py
trio_websockets/client.py
trio_websockets/exceptions.py
trio_websockets/protocol.py
trio_websockets/server.py
trio_websockets/test_client_server.py
trio_websockets/test_exceptions.py
trio_websockets/test_protocol.py
trio_websockets/test_uri.py
trio_websockets/uri.py
trio_websockets/utils.py
trio_websockets/version.py
trio_websockets.egg-info/PKG-INFO
trio_websockets.egg-info/SOURCES.txt
trio_websockets.egg-info/dependency_links.txt
trio_websockets.egg-info/requires.txt
trio_websockets.egg-info/top_level.txt
trio_websockets.egg-info/zip-safe
trio_websockets/py35/__init__.py
trio_websockets/py35/_test_client_server.py
trio_websockets/py36/__init__.py
trio_websockets/py36/_test_client_server.py
trio_websockets/py36/protocol.py