Metadata-Version: 1.2
Name: trio-websockets
Version: 0.2
Summary: An implementation of the WebSocket Protocol (RFC 6455 & 7692)
Home-page: https://github.com/miracle2k/trio-websockets
Author: Michael Elsdorfer
Author-email: michael@elsdorfer.com
License: BSD
Platform: UNKNOWN
Classifier: Development Status :: 5 - Production/Stable
Classifier: Environment :: Web Environment
Classifier: Intended Audience :: Developers
Classifier: License :: OSI Approved :: BSD License
Classifier: Operating System :: OS Independent
Classifier: Programming Language :: Python
Classifier: Programming Language :: Python :: 3
Classifier: Programming Language :: Python :: 3.5
Classifier: Programming Language :: Python :: 3.6
Requires-Python: >=3.4
